{
  "attributes": {
    "title": "Real-Time Sensor Data Table",
    "visState": "{\"title\":\"Real-Time Sensor Data Table\",\"type\":\"table\",\"aggs\":[{\"id\":\"1\",\"enabled\":true,\"type\":\"count\",\"params\":{},\"schema\":\"metric\"},{\"id\":\"2\",\"enabled\":true,\"type\":\"avg\",\"params\":{\"field\":\"motor_temp_c\"},\"schema\":\"metric\"},{\"id\":\"3\",\"enabled\":true,\"type\":\"avg\",\"params\":{\"field\":\"power_consumption_kw\"},\"schema\":\"metric\"},{\"id\":\"4\",\"enabled\":true,\"type\":\"avg\",\"params\":{\"field\":\"health_score\"},\"schema\":\"metric\"},{\"id\":\"5\",\"enabled\":true,\"type\":\"terms\",\"params\":{\"field\":\"crane_id.keyword\",\"orderBy\":\"1\",\"order\":\"desc\",\"size\":20},\"schema\":\"bucket\"}],\"params\":{\"perPage\":10,\"showPartialRows\":false,\"showMetricsAtAllLevels\":false,\"sort\":{\"columnIndex\":null,\"direction\":null},\"showTotal\":true,\"totalFunc\":\"avg\"}}",
    "uiStateJSON": "{}",
    "description": "Tabular view of crane sensor data",
    "kibanaSavedObjectMeta": {"searchSourceJSON": "{\"query\":{\"query\":\"\",\"language\":\"kuery\"},\"filter\":[],\"indexRefName\":\"kibanaSavedObjectMeta.searchSourceJSON.index\"}"}
  },
  "references": [{"name": "kibanaSavedObjectMeta.searchSourceJSON.index", "type": "index-pattern", "id": "929c7f13-8569-481c-b4f1-9f6b687c7f22"}]
}